anomaly_pipeline/__init__.py
anomaly_pipeline/main.py
anomaly_pipeline/pipeline.py
anomaly_pipeline/helpers/DB_scan.py
anomaly_pipeline/helpers/IQR.py
anomaly_pipeline/helpers/MAD.py
anomaly_pipeline/helpers/Preprocessing.py
anomaly_pipeline/helpers/STD.py
anomaly_pipeline/helpers/__init__.py
anomaly_pipeline/helpers/baseline.py
anomaly_pipeline/helpers/cluster_functions.py
anomaly_pipeline/helpers/evaluation_info.py
anomaly_pipeline/helpers/evaluation_plots.py
anomaly_pipeline/helpers/ewma.py
anomaly_pipeline/helpers/fb_prophet.py
anomaly_pipeline/helpers/help_anomaly.py
anomaly_pipeline/helpers/iso_forest_general.py
anomaly_pipeline/helpers/iso_forest_timeseries.py
anomaly_pipeline/helpers/percentile.py
anomaly_pipeline-0.1.60.dist-info/METADATA
anomaly_pipeline-0.1.60.dist-info/WHEEL
anomaly_pipeline-0.1.60.dist-info/entry_points.txt
anomaly_pipeline-0.1.60.dist-info/top_level.txt
anomaly_pipeline-0.1.60.dist-info/RECORD
