Metadata-Version: 2.4
Name: anomaly_pipeline
Version: 0.1.60
Summary: Ensemble framework for detecting outliers in grouped time-series data
Classifier: Programming Language :: Python :: 3
Classifier: License :: OSI Approved :: MIT License
Classifier: Operating System :: OS Independent
Classifier: Intended Audience :: Science/Research
Classifier: Topic :: Scientific/Engineering :: Artificial Intelligence
Requires-Python: >=3.8
Requires-Dist: pandas
Requires-Dist: numpy<2
Requires-Dist: joblib
Requires-Dist: prophet
Requires-Dist: scikit-learn
Requires-Dist: google-cloud-bigquery
Requires-Dist: google-cloud-storage
Requires-Dist: statsmodels
Requires-Dist: plotly
Requires-Dist: pandas-gbq
Requires-Dist: gcsfs
Dynamic: classifier
Dynamic: description
Dynamic: description-content-type
Dynamic: requires-dist
Dynamic: requires-python
Dynamic: summary
